drb/drivers/netcdf/__init__.py
drb/drivers/netcdf/_version.py
drb/drivers/netcdf/netcdf.py
drb/drivers/netcdf/netcdf_node_factory.py
drb/exceptions/netcdf.py
drb/topics/netcdf/__init__.py
drb/topics/netcdf/cortex.yml
drb_driver_netcdf-1.3.0.dist-info/LICENCE.txt
drb_driver_netcdf-1.3.0.dist-info/METADATA
drb_driver_netcdf-1.3.0.dist-info/WHEEL
drb_driver_netcdf-1.3.0.dist-info/entry_points.txt
drb_driver_netcdf-1.3.0.dist-info/top_level.txt
drb_driver_netcdf-1.3.0.dist-info/RECORD
