Metadata-Version: 2.1
Name: drb-driver-netcdf
Version: 1.3.0
Summary: DRB NetCDF Driver
Author: GAEL Systems
Author-email: drb-python@gael.fr
License: LGPLv3
Project-URL: Documentation, http://drb-python.gitlab.io/impl/netcdf
Project-URL: Source, https://gitlab.com/drb-python/impl/netcdf
Classifier: Programming Language :: Python :: 3.8
Classifier: Environment :: Plugins
Classifier: License :: OSI Approved :: GNU Lesser General Public License v3 (LGPLv3)
Requires-Python: >=3.8
License-File: LICENCE.txt
Requires-Dist: drb ~=2.2.0
Requires-Dist: netCDF4 >=1.5.7
Requires-Dist: numpy >=1.21.2
Requires-Dist: xarray >=0.19.0
